README.md
setup.cfg
setup.py
EasyModbus.egg-info/PKG-INFO
EasyModbus.egg-info/SOURCES.txt
EasyModbus.egg-info/dependency_links.txt
EasyModbus.egg-info/requires.txt
EasyModbus.egg-info/top_level.txt
EasyModbus.egg-info/.idea/.gitignore
EasyModbus.egg-info/.idea/EasyModbus.egg-info.iml
EasyModbus.egg-info/.idea/misc.xml
EasyModbus.egg-info/.idea/modules.xml
EasyModbus.egg-info/.idea/vcs.xml
EasyModbus.egg-info/.idea/workspace.xml
EasyModbus.egg-info/.idea/inspectionProfiles/Project_Default.xml
EasyModbus.egg-info/.idea/inspectionProfiles/profiles_settings.xml
easymodbus/__init__.py
easymodbus/easyModbusGUI.py
easymodbus/modbusClient.py
easymodbus/modbusException.py
easymodbus/modbus_protocol.py
easymodbus/run.py