Metadata-Version: 2.1
Name: EasyModbus
Version: 2.0.1
Summary: THE standard library for Modbus RTU and Modbus TCP - See www.EasyModbusTCP.NET for documentation
Home-page: http://www.easymodbustcp.net
Author: Stefan Rossmann
Author-email: info@rossmann-engineering.de
License: MIT
Keywords: easymodbus modbus serial RTU TCP EasyModbusTCP
Platform: UNKNOWN
Classifier: Development Status :: 5 - Production/Stable
Classifier: Environment :: Console
Classifier: Environment :: Web Environment
Classifier: Intended Audience :: Developers
Classifier: Intended Audience :: Education
Classifier: License :: OSI Approved :: MIT License
Classifier: Operating System :: MacOS :: MacOS X
Classifier: Operating System :: Microsoft :: Windows
Classifier: Operating System :: POSIX
Classifier: Programming Language :: Python
Classifier: Topic :: Scientific/Engineering
Classifier: Topic :: Software Development :: Libraries
Classifier: Topic :: Utilities
